configlookup/__init__.py
configlookup/main.py
configlookup/reader.py
configlookup/singleton.py
configlookup/utils.py
configlookup/overrider/__init__.py
configlookup/overrider/abstract_overrider.py
configlookup/overrider/environment_overrider.py
configlookup-0.1.7.dist-info/LICENSE
configlookup-0.1.7.dist-info/METADATA
configlookup-0.1.7.dist-info/WHEEL
configlookup-0.1.7.dist-info/top_level.txt
configlookup-0.1.7.dist-info/RECORD
