Metadata-Version: 2.1
Name: configlookup
Version: 0.1.7
Summary: This package provides a singleton to read configuration values from json, env var, etc...
Home-page: https://github.com/tgedr/configlookup
Author: joao tiago viegas
Author-email: jtviegas.js@gmail.com
License: Unlicense
Platform: UNKNOWN
Classifier: Programming Language :: Python :: 3
Classifier: Programming Language :: Python :: 3.7
License-File: LICENSE
Requires-Dist: pytest
